gif2tty/__init__.py
gif2tty/__main__.py
gif2tty/__version__.py
gif2tty/ascii.py
gif2tty/csi.py
gif2tty/gif.py
gif2tty/tty.py
gif2tty/utils.py
test/__init__.py
gif2tty-0.1.5.dist-info/LICENSE
gif2tty-0.1.5.dist-info/METADATA
gif2tty-0.1.5.dist-info/WHEEL
gif2tty-0.1.5.dist-info/entry_points.txt
gif2tty-0.1.5.dist-info/top_level.txt
gif2tty-0.1.5.dist-info/RECORD
