Metadata-Version: 2.1
Name: gif2tty
Version: 0.1.5
Summary: play gif on tty
Home-page: https://github.com/zyongqing/gif2tty
Author: zyongqing
Author-email: zyongqing@gmail.com
License: Apache 2.0
Platform: UNKNOWN
Classifier: License :: OSI Approved :: Apache Software License
Classifier: Programming Language :: Python
Classifier: Programming Language :: Python :: 3
Classifier: Programming Language :: Python :: 3.6
Classifier: Programming Language :: Python :: Implementation :: CPython
Classifier: Programming Language :: Python :: Implementation :: PyPy
Requires-Python: >=3.6.0
Requires-Dist: pillow
Requires-Dist: scipy
